dioptas/__init__.py
dioptas/_version.py
dioptas/excepthook.py
dioptas/paths.py
dioptas/controller/CalibrationController.py
dioptas/controller/ConfigurationController.py
dioptas/controller/MainController.py
dioptas/controller/MapController.py
dioptas/controller/MaskController.py
dioptas/controller/__init__.py
dioptas/controller/integration/BackgroundController.py
dioptas/controller/integration/BatchController.py
dioptas/controller/integration/CorrectionController.py
dioptas/controller/integration/EpicsController.py
dioptas/controller/integration/ImageController.py
dioptas/controller/integration/IntegrationController.py
dioptas/controller/integration/MapController.py
dioptas/controller/integration/OptionsController.py
dioptas/controller/integration/PatternController.py
dioptas/controller/integration/PhotoConfig.py
dioptas/controller/integration/__init__.py
dioptas/controller/integration/econfig.py
dioptas/controller/integration/overlay/OverlayController.py
dioptas/controller/integration/overlay/OverlayInPatternController.py
dioptas/controller/integration/phase/JcpdsEditorController.py
dioptas/controller/integration/phase/PhaseController.py
dioptas/controller/integration/phase/PhaseInBatchController.py
dioptas/controller/integration/phase/PhaseInCakeController.py
dioptas/controller/integration/phase/PhaseInPatternController.py
dioptas/controller/integration/phase/__init__.py
dioptas/model/BatchModel.py
dioptas/model/CalibrationModel.py
dioptas/model/Configuration.py
dioptas/model/DioptasModel.py
dioptas/model/ImgModel.py
dioptas/model/MapModel.py
dioptas/model/MapModel2.py
dioptas/model/MaskModel.py
dioptas/model/OverlayModel.py
dioptas/model/PatternModel.py
dioptas/model/PhaseModel.py
dioptas/model/__init__.py
dioptas/model/loader/FabioLoader.py
dioptas/model/loader/KaraboLoader.py
dioptas/model/loader/LambdaLoader.py
dioptas/model/loader/__init__.py
dioptas/model/loader/hdf5Loader.py
dioptas/model/loader/spe.py
dioptas/model/util/HelperModule.py
dioptas-0.7.2.dist-info/licenses/LICENSE.txt
dioptas-0.7.2.dist-info/METADATA
dioptas-0.7.2.dist-info/WHEEL
dioptas-0.7.2.dist-info/entry_points.txt
dioptas-0.7.2.dist-info/top_level.txt
dioptas-0.7.2.dist-info/RECORD
