Metadata-Version: 2.4
Name: dioptas
Version: 0.7.2
Summary: GUI program for reduction and exploration of 2D X-ray diffraction data
Author-email: Clemens Prescher <clemens.prescher@gmail.com>
License: GPL-3.0
Classifier: Intended Audience :: Science/Research
Classifier: Operating System :: OS Independent
Classifier: Programming Language :: Python
Classifier: License :: OSI Approved :: GNU General Public License v3 (GPLv3)
Classifier: Topic :: Scientific/Engineering
Classifier: Topic :: Scientific/Engineering :: Physics
Classifier: Topic :: Scientific/Engineering :: Chemistry
Classifier: Topic :: Scientific/Engineering :: Visualization
Classifier: Topic :: Scientific/Engineering :: Information Analysis
Requires-Python: <3.14,>=3.10
License-File: LICENSE.txt
Requires-Dist: EXtra-data<2.0,>=1.13.0; sys_platform == "linux"
Requires-Dist: h5py<4.0,>=3.13.0
Requires-Dist: hdf5plugin<6.0,>=5.0.0
Requires-Dist: lmfit<2.0,>=1.3.3
Requires-Dist: pandas<3.0,>=2.1.1
Requires-Dist: psutil<6.0,>=5.9.5
Requires-Dist: PyCifRW<6.0,>=5.0.0
Requires-Dist: PyQt6<7.0,>=6.8
Requires-Dist: pyfai==2025.3.0
Requires-Dist: pyqtgraph<0.14,>=0.13.7
Requires-Dist: pyshortcuts<2.0,>=1.8.1
Requires-Dist: QtPy<3.0,>=2.4.3
Requires-Dist: scikit-image<0.23,>=0.22.0; python_version == "3.10"
Requires-Dist: scikit-image<0.27,>=0.26.0; python_version >= "3.11"
Requires-Dist: sharedmem<0.4,>=0.3.8
Requires-Dist: watchdog<7.0,>=6.0.0
Requires-Dist: pyopengl<4.0,>=3.1.7
Requires-Dist: pyopengl-accelerate<4.0,>=3.1.7
Requires-Dist: xypattern<2.0,>=1.2.2
Requires-Dist: numpy<2.0,>=1.26.0; python_version == "3.10"
Requires-Dist: numpy<3.0,>=2.0; python_version >= "3.11"
Requires-Dist: scipy<2.0,>=1.11.3; python_version == "3.10"
Requires-Dist: scipy<2.0,>=1.16.3; python_version >= "3.11"
Requires-Dist: numexpr<3.0,>=2.10.2
Requires-Dist: qt-material<3.0,>=2.14
Provides-Extra: test
Requires-Dist: pytest<9.0,>=7.4.0; extra == "test"
Requires-Dist: pytest-qt<5.0,>=4.4.0; extra == "test"
Requires-Dist: mock<6.0,>=5.1.0; extra == "test"
Requires-Dist: pytest-xdist>=3.8.0; extra == "test"
Dynamic: license-file
